clusterbootstraps/__init__.py
clusterbootstraps/pair.py
clusterbootstraps/wild.py
clusterbootstraps-0.1.10.dist-info/LICENSE
clusterbootstraps-0.1.10.dist-info/METADATA
clusterbootstraps-0.1.10.dist-info/WHEEL
clusterbootstraps-0.1.10.dist-info/top_level.txt
clusterbootstraps-0.1.10.dist-info/RECORD
