Metadata-Version: 2.1
Name: clusterbootstraps
Version: 0.1.10
Summary: UNKNOWN
Home-page: https://github.com/Bank1999/clusterbootstraps
Author: Bingkun Lin/Shiyue Shen/Ziyi Zhan/Zizhong Yan
Author-email: linbingkun.iesr18u@foxmail.com
License: MIT
Platform: UNKNOWN
Classifier: License :: OSI Approved :: MIT License
Classifier: Programming Language :: Python :: 3
Classifier: Programming Language :: Python :: 3.7
Requires-Dist: numpy
Requires-Dist: pandas
Requires-Dist: statsmodels
Requires-Dist: prettytable
